loglu_pytorch/__init__.py
loglu_pytorch/loglu_pytorch.py
loglu_pytorch-1.0.0.dist-info/METADATA
loglu_pytorch-1.0.0.dist-info/WHEEL
loglu_pytorch-1.0.0.dist-info/top_level.txt
loglu_pytorch-1.0.0.dist-info/RECORD
