Metadata-Version: 2.1
Name: loglu-pytorch
Version: 1.0.0
Summary: ZenGrad: A gradient descent method focused on stability, smooth updates, and efficient, adaptive learning.
Home-page: https://github.com/Poorni-Murumuri/loglu-pytorch
Author: Murumuri Naga Poorni 
Author-email: poorni.m0405@gmail.com
License: Apache-2.0
Classifier: Programming Language :: Python :: 3
Classifier: License :: OSI Approved :: Apache Software License
Classifier: Operating System :: OS Independent
Classifier: Intended Audience :: Developers
Classifier: Intended Audience :: Science/Research
Classifier: Topic :: Scientific/Engineering :: Artificial Intelligence
Requires-Python: >=3.6
Requires-Dist: torch>=1.6.0
